[{"kind": "Listing", "data": {"after": null, "whitelist_status": null, "modhash": "", "dist": 1, "children": [{"kind": "t3", "data": {"is_crosspostable": false, "subreddit_id": "t5_2qpzs", "approved_at_utc": null, "mod_reason_by": null, "banned_by": null, "removal_reason": null, "subreddit": "SuicideWatch", "selftext_html": "&lt;!-- SC_OFF --&gt;&lt;div class=\"md\"&gt;&lt;p&gt;i wish i was dead. i legitimately believe that if i found a button that could end my life instantly when pressed, i would press it. i don&amp;#39;t mean just now, i mean any time. i would press it right after waking up. i would press it while getting ready for bed. i would press it while taking a difficult test. i would press it while hanging out with my friends. i would press it while talking to my teacher. i would press it while talking to my crush. i would press it while taking a shower. i would press it when i&amp;#39;m taking a walk on a beautiful summer day. i would press it anywhere, because i know, even in the good moments, that i&amp;#39;m better off dead. i&amp;#39;m not joking and i&amp;#39;m not exaggerating. if this button appeared in front of me right now, i would stop typing instantly and press it.&lt;/p&gt;\n\n&lt;p&gt;every day is the same as the day before. there are no big changes, and i&amp;#39;m just getting really fucking bored of it. is this life? i don&amp;#39;t feel alive. when i&amp;#39;m at school i see everyone smiling and laughing all the fucking time. i&amp;#39;m serious, everyone is happy. it&amp;#39;s all one big happy family that i&amp;#39;m not a part of because i don&amp;#39;t fit into it. i walk past them every single day and i always wonder what their secret is. how can they be so happy, so content with their lives? the way they all live isn&amp;#39;t much different than the way i live, but somehow they&amp;#39;re all able to laugh and smile and just be happy. why? what am i missing? it&amp;#39;s just so alienating to see how happy everyone is when i&amp;#39;m not, and it makes me feel so much more alone.&lt;/p&gt;\n\n&lt;p&gt;nothing brings me joy. some things make me smile, some things make chuckle, but nothing brings me joy. i know others who experience joy every day. deep, meaningful joy. the type of happiness that defies logic, the kind of thing that can make a person happy even in the face of hopelessness. i sit beside these people in school. sometimes we&amp;#39;re not 3 feet apart from each other. how can such happiness exist so close to such emptiness? &lt;/p&gt;\n\n&lt;p&gt;my life is empty. i&amp;#39;m empty. i can&amp;#39;t think of any better word to describe how i feel than empty. i&amp;#39;m not sad, i&amp;#39;m not miserable, i&amp;#39;m just empty. i feel hollow and cold, like wind could blow right through me. i don&amp;#39;t feel like a human being. i feel like any moment i could fall and not be able to find the motivation to get up.&lt;/p&gt;\n\n&lt;p&gt;this is how i live, if living is really what you can call it. i&amp;#39;m so bored of feeling this way. everyone feels like this sometimes and that&amp;#39;s normal. but i&amp;#39;ve felt like this for way too long, for years now. this is my life, isn&amp;#39;t it? should i have some authority as to what i do with my life? is 17 too young to die? i don&amp;#39;t think it is. people die at all different kinds of ages. some die when they&amp;#39;re 80, some die in their teens. it&amp;#39;s better to live a short unhappy life than a long unhappy life, isn&amp;#39;t it? some people say it gets better, but right now, i don&amp;#39;t care if i get better. i just want to die. i would absolutely love to see that button right about now.&lt;/p&gt;\n&lt;/div&gt;&lt;!-- SC_ON --&gt;", "selftext": "i wish i was dead. i legitimately believe that if i found a button that could end my life instantly when pressed, i would press it. i don't mean just now, i mean any time. i would press it right after waking up. i would press it while getting ready for bed. i would press it while taking a difficult test. i would press it while hanging out with my friends. i would press it while talking to my teacher. i would press it while talking to my crush. i would press it while taking a shower. i would press it when i'm taking a walk on a beautiful summer day. i would press it anywhere, because i know, even in the good moments, that i'm better off dead. i'm not joking and i'm not exaggerating. if this button appeared in front of me right now, i would stop typing instantly and press it.\n\nevery day is the same as the day before. there are no big changes, and i'm just getting really fucking bored of it. is this life? i don't feel alive. when i'm at school i see everyone smiling and laughing all the fucking time. i'm serious, everyone is happy. it's all one big happy family that i'm not a part of because i don't fit into it. i walk past them every single day and i always wonder what their secret is. how can they be so happy, so content with their lives? the way they all live isn't much different than the way i live, but somehow they're all able to laugh and smile and just be happy. why? what am i missing? it's just so alienating to see how happy everyone is when i'm not, and it makes me feel so much more alone.\n\nnothing brings me joy. some things make me smile, some things make chuckle, but nothing brings me joy. i know others who experience joy every day. deep, meaningful joy. the type of happiness that defies logic, the kind of thing that can make a person happy even in the face of hopelessness. i sit beside these people in school. sometimes we're not 3 feet apart from each other. how can such happiness exist so close to such emptiness? \n\nmy life is empty. i'm empty. i can't think of any better word to describe how i feel than empty. i'm not sad, i'm not miserable, i'm just empty. i feel hollow and cold, like wind could blow right through me. i don't feel like a human being. i feel like any moment i could fall and not be able to find the motivation to get up.\n\nthis is how i live, if living is really what you can call it. i'm so bored of feeling this way. everyone feels like this sometimes and that's normal. but i've felt like this for way too long, for years now. this is my life, isn't it? should i have some authority as to what i do with my life? is 17 too young to die? i don't think it is. people die at all different kinds of ages. some die when they're 80, some die in their teens. it's better to live a short unhappy life than a long unhappy life, isn't it? some people say it gets better, but right now, i don't care if i get better. i just want to die. i would absolutely love to see that button right about now.", "likes": null, "suggested_sort": null, "mod_note": null, "user_reports": [], "secure_media": null, "is_reddit_media_domain": false, "saved": false, "id": "5wt0uf", "banned_at_utc": null, "mod_reason_title": null, "view_count": null, "archived": true, "clicked": false, "no_follow": true, "author": "djeiowkdjdjdke", "num_crossposts": 0, "link_flair_text": null, "can_mod_post": false, "send_replies": true, "pinned": false, "score": 3, "approved_by": null, "over_18": false, "domain": "self.SuicideWatch", "hidden": false, "num_comments": 1, "thumbnail": "", "hide_score": false, "edited": false, "link_flair_css_class": null, "author_flair_css_class": null, "contest_mode": false, "gilded": 0, "locked": false, "downs": 0, "brand_safe": false, "subreddit_subscribers": 83421, "secure_media_embed": {}, "media_embed": {}, "stickied": false, "can_gild": false, "is_self": true, "parent_whitelist_status": "no_ads", "name": "t3_5wt0uf", "spoiler": false, "permalink": "/r/SuicideWatch/comments/5wt0uf/im_only_17_but_my_mind_is_old/", "subreddit_type": "public", "whitelist_status": "no_ads", "report_reasons": null, "created": 1488370439.0, "url": "https://www.reddit.com/r/SuicideWatch/comments/5wt0uf/im_only_17_but_my_mind_is_old/", "author_flair_text": null, "quarantine": false, "title": "I'm only 17 but my mind is old.", "created_utc": 1488341639.0, "subreddit_name_prefixed": "r/SuicideWatch", "distinguished": null, "media": null, "upvote_ratio": 1.0, "mod_reports": [], "visited": false, "num_reports": null, "is_video": false, "ups": 3}}], "before": null}}, {"kind": "Listing", "data": {"after": null, "whitelist_status": null, "modhash": "", "dist": null, "children": [], "before": null}}]