[{"kind": "Listing", "data": {"after": null, "whitelist_status": null, "modhash": "", "dist": 1, "children": [{"kind": "t3", "data": {"is_crosspostable": false, "subreddit_id": "t5_2qm0x", "approved_at_utc": null, "mod_reason_by": null, "banned_by": null, "removal_reason": null, "subreddit": "ptsd", "selftext_html": "&lt;!-- SC_OFF --&gt;&lt;div class=\"md\"&gt;&lt;p&gt;THEN&lt;/p&gt;\n\n&lt;p&gt;When my eighteen-year-old son moved out (many years ago), I found myself living alone for the first time in my life, in the midst of a brutal Baltimore winter.&lt;/p&gt;\n\n&lt;p&gt;falling snow&lt;/p&gt;\n\n&lt;p&gt;I had turned on every light, sat in the living room and stared at the TV all night long, afraid to close my eyes. Plus, being stuck in a wheelchair imprisoned me. Nightmares of that monster trafficker, Shane, his gang of pimps, and my abusive husband, Armando, finding me tortured my mind.&lt;/p&gt;\n\n&lt;p&gt;I rolled around my apartment, checking and rechecking every door and window, tightening the locks repeatedly. Dancing shadows on the shades unglued me, my racing heart nearly exploded. I tried reading Psalm twenty-three and listening to soothing music; but nothing helped abate my panic attacks.&lt;/p&gt;\n\n&lt;p&gt;depressed woman in wheelchair&lt;/p&gt;\n\n&lt;p&gt;The abysmal days of isolation drove me batty. I picked up magazines, unable to get beyond the first page before tossing them aside. With no appetite or wish to take care of myself, I became a mess, emaciated and dirty. The radiator generated little heat, so my paralyzed legs and feet froze. It led me to wonder if God was punishing me.&lt;/p&gt;\n\n&lt;p&gt;I pried my memory, trying to figure out what I had done wrong.&lt;/p&gt;\n\n&lt;p&gt;I was born, neglected by an uninterested mother and an alcoholic father, molested by a teenage boy at the age of eleven, gang raped by three upper class men in ninth grade, kidnapped and sold to sex traffickers at eighteen, suffered through two extremely abusive marriages, and then became paralyzed, all the time blaming myself believing I deserved it.&lt;/p&gt;\n\n&lt;p&gt;Nevertheless, a kind of hope ignited in me. Like an ember, fading and brightening again, it burned quietly. Though I\u2019ve often felt as if my mind would disintegrate, somehow it has not.&lt;/p&gt;\n\n&lt;p&gt;hope hope&lt;/p&gt;\n\n&lt;hr/&gt;\n\n&lt;p&gt;NOW&lt;/p&gt;\n\n&lt;p&gt;Sudden noises, a knock at the front door, the turn of a key among other things still make me jump. Forgetting I am safe, it always takes me a moment to readjust. I sleep with my face and head completely covered, even though I am claustrophobic.&lt;/p&gt;\n\n&lt;p&gt;I\u2019m stuck inside a body that doesn\u2019t move and spend nearly 24/7 hours laying on an uncomfortable specialty mattress that helps heal pressure wounds. But, it\u2019s painful. My mid section, including my back, sink into the twenty vinyl cells of a low air loss mattress, which constantly moves to stimulate circulation. My neck \u2013 continually bent because the air cells in the head section stay in a static place \u2013 my shoulders, slouched and pinched. You\u2019d be surprised how hard those air-filled cells are, even though it feels like I\u2019m balancing myself on a deflating raft in turbulent waters. So unpleasant.&lt;/p&gt;\n\n&lt;p&gt;my mattess&lt;/p&gt;\n\n&lt;p&gt;The sound of the mattress pump reverberates throughout our condo, a loud annoying white noise that never ceases.&lt;/p&gt;\n\n&lt;hr/&gt;\n\n&lt;p&gt;Outgoing and friendly, I enjoy talking to people very much, yet I\u2019m socially dwarfed. It\u2019s a dichotomy that confuses me. When no one calls or visits, I feel rejected, however, I prefer my solace. I lack self-esteem and self-confidence. In fact, they are non-existent in my life although I am fortunate to have a handful of supportive friends. Writing helps but it does not ward off abrupt panic attacks or bouts of depression that blind side me.&lt;/p&gt;\n\n&lt;p&gt;gun&lt;/p&gt;\n\n&lt;p&gt;Triggers happen via memories or images, while I\u2019m typing, listening to a song, or watching TV. Bullets fly out of nowhere and pummel me, throwing me into an abysm. And whatever happy moment I\u2019m enjoying turns to darkness.&lt;/p&gt;\n\n&lt;p&gt;Rather than reach out to the one I call God, I hide myself under my covers for hours and listen to extremely depressing songs like Whiter Shade of Pale and N.U.M.B. During those times, I long to wither away and die. That is when I pray to God to release me from this life of ongoing anguish and misery.&lt;/p&gt;\n\n&lt;p&gt;I\u2019ve sought therapy to no avail, but I\u2019m still hopeful. Also, many times a mysterious joy invades my heart and pulls me out of the muck. And I sometimes hear a whisper, from a source I cannot see, that strengthens me. It baffles me how I can bounce off a mountain into a pit in a moment\u2019s time.&lt;/p&gt;\n\n&lt;p&gt;Because some people have certain expectations of me, guilt and shame remain constant companions. Many say my faith should be sufficient, but those that do lack understanding, empathy, and identification. I pass no judgement on them and hope they pass none on me.&lt;/p&gt;\n\n&lt;p&gt;Although the ember of hope keeps burning quietly, my heart quivers as I share these secrets publicly. However the audience I seek for this entry are those who suffer as I do. Maybe, together, we can help one another heal. As for others who read this post, I thank you.&lt;/p&gt;\n\n&lt;p&gt;burning candle&lt;/p&gt;\n\n&lt;p&gt;\u201cI feel like the one insight that\u2019s extremely comforting to me about the world is that we all share the same pool of emotion that we draw from.\u201d Abigail Washburn&lt;/p&gt;\n&lt;/div&gt;&lt;!-- SC_ON --&gt;", "selftext": "THEN\n\nWhen my eighteen-year-old son moved out (many years ago), I found myself living alone for the first time in my life, in the midst of a brutal Baltimore winter.\n\nfalling snow\n\nI had turned on every light, sat in the living room and stared at the TV all night long, afraid to close my eyes. Plus, being stuck in a wheelchair imprisoned me. Nightmares of that monster trafficker, Shane, his gang of pimps, and my abusive husband, Armando, finding me tortured my mind.\n\nI rolled around my apartment, checking and rechecking every door and window, tightening the locks repeatedly. Dancing shadows on the shades unglued me, my racing heart nearly exploded. I tried reading Psalm twenty-three and listening to soothing music; but nothing helped abate my panic attacks.\n\ndepressed woman in wheelchair\n\nThe abysmal days of isolation drove me batty. I picked up magazines, unable to get beyond the first page before tossing them aside. With no appetite or wish to take care of myself, I became a mess, emaciated and dirty. The radiator generated little heat, so my paralyzed legs and feet froze. It led me to wonder if God was punishing me.\n\nI pried my memory, trying to figure out what I had done wrong.\n\nI was born, neglected by an uninterested mother and an alcoholic father, molested by a teenage boy at the age of eleven, gang raped by three upper class men in ninth grade, kidnapped and sold to sex traffickers at eighteen, suffered through two extremely abusive marriages, and then became paralyzed, all the time blaming myself believing I deserved it.\n\nNevertheless, a kind of hope ignited in me. Like an ember, fading and brightening again, it burned quietly. Though I\u2019ve often felt as if my mind would disintegrate, somehow it has not.\n\nhope hope\n\n_______________________________________________\n\nNOW\n\nSudden noises, a knock at the front door, the turn of a key among other things still make me jump. Forgetting I am safe, it always takes me a moment to readjust. I sleep with my face and head completely covered, even though I am claustrophobic.\n\nI\u2019m stuck inside a body that doesn\u2019t move and spend nearly 24/7 hours laying on an uncomfortable specialty mattress that helps heal pressure wounds. But, it\u2019s painful. My mid section, including my back, sink into the twenty vinyl cells of a low air loss mattress, which constantly moves to stimulate circulation. My neck \u2013 continually bent because the air cells in the head section stay in a static place \u2013 my shoulders, slouched and pinched. You\u2019d be surprised how hard those air-filled cells are, even though it feels like I\u2019m balancing myself on a deflating raft in turbulent waters. So unpleasant.\n\nmy mattess\n\nThe sound of the mattress pump reverberates throughout our condo, a loud annoying white noise that never ceases.\n\n______________________________________________\n\nOutgoing and friendly, I enjoy talking to people very much, yet I\u2019m socially dwarfed. It\u2019s a dichotomy that confuses me. When no one calls or visits, I feel rejected, however, I prefer my solace. I lack self-esteem and self-confidence. In fact, they are non-existent in my life although I am fortunate to have a handful of supportive friends. Writing helps but it does not ward off abrupt panic attacks or bouts of depression that blind side me.\n\ngun\n\nTriggers happen via memories or images, while I\u2019m typing, listening to a song, or watching TV. Bullets fly out of nowhere and pummel me, throwing me into an abysm. And whatever happy moment I\u2019m enjoying turns to darkness.\n\nRather than reach out to the one I call God, I hide myself under my covers for hours and listen to extremely depressing songs like Whiter Shade of Pale and N.U.M.B. During those times, I long to wither away and die. That is when I pray to God to release me from this life of ongoing anguish and misery.\n\nI\u2019ve sought therapy to no avail, but I\u2019m still hopeful. Also, many times a mysterious joy invades my heart and pulls me out of the muck. And I sometimes hear a whisper, from a source I cannot see, that strengthens me. It baffles me how I can bounce off a mountain into a pit in a moment\u2019s time.\n\nBecause some people have certain expectations of me, guilt and shame remain constant companions. Many say my faith should be sufficient, but those that do lack understanding, empathy, and identification. I pass no judgement on them and hope they pass none on me.\n\nAlthough the ember of hope keeps burning quietly, my heart quivers as I share these secrets publicly. However the audience I seek for this entry are those who suffer as I do. Maybe, together, we can help one another heal. As for others who read this post, I thank you.\n\nburning candle\n\n\u201cI feel like the one insight that\u2019s extremely comforting to me about the world is that we all share the same pool of emotion that we draw from.\u201d Abigail Washburn", "likes": null, "suggested_sort": "new", "mod_note": null, "user_reports": [], "secure_media": null, "is_reddit_media_domain": false, "saved": false, "id": "3j5z9p", "banned_at_utc": null, "mod_reason_title": null, "view_count": null, "archived": true, "clicked": false, "no_follow": true, "author": "inmercyrejoice", "num_crossposts": 0, "link_flair_text": null, "can_mod_post": false, "send_replies": true, "pinned": false, "score": 4, "approved_by": null, "over_18": false, "domain": "self.ptsd", "hidden": false, "num_comments": 5, "thumbnail": "", "hide_score": false, "edited": false, "link_flair_css_class": null, "author_flair_css_class": null, "contest_mode": false, "gilded": 0, "locked": false, "downs": 0, "brand_safe": false, "subreddit_subscribers": 13131, "secure_media_embed": {}, "media_embed": {}, "stickied": false, "can_gild": false, "is_self": true, "parent_whitelist_status": null, "name": "t3_3j5z9p", "spoiler": false, "permalink": "/r/ptsd/comments/3j5z9p/my_struggles_with_ptsd_depression_faith_and/", "subreddit_type": "public", "whitelist_status": null, "report_reasons": null, "created": 1441102153.0, "url": "https://www.reddit.com/r/ptsd/comments/3j5z9p/my_struggles_with_ptsd_depression_faith_and/", "author_flair_text": null, "quarantine": false, "title": "My Struggles with PTSD, Depression, Faith, and Maintaining a Smile", "created_utc": 1441073353.0, "subreddit_name_prefixed": "r/ptsd", "distinguished": null, "media": null, "upvote_ratio": 0.75, "mod_reports": [], "visited": false, "num_reports": null, "is_video": false, "ups": 4}}], "before": null}}, {"kind": "Listing", "data": {"after": null, "whitelist_status": null, "modhash": "", "dist": null, "children": [{"kind": "t1", "data": {"subreddit_id": "t5_2qm0x", "approved_at_utc": null, "ups": 2, "mod_reason_by": null, "banned_by": null, "removal_reason": null, "link_id": "t3_3j5z9p", "likes": null, "no_follow": true, "replies": {"kind": "Listing", "data": {"after": null, "whitelist_status": null, "modhash": "", "dist": null, "children": [{"kind": "t1", "data": {"subreddit_id": "t5_2qm0x", "approved_at_utc": null, "ups": 1, "mod_reason_by": null, "banned_by": null, "removal_reason": null, "link_id": "t3_3j5z9p", "likes": null, "no_follow": true, "replies": {"kind": "Listing", "data": {"after": null, "whitelist_status": null, "modhash": "", "dist": null, "children": [{"kind": "t1", "data": {"subreddit_id": "t5_2qm0x", "approved_at_utc": null, "ups": 1, "mod_reason_by": null, "banned_by": null, "removal_reason": null, "link_id": "t3_3j5z9p", "likes": null, "no_follow": true, "replies": "", "user_reports": [], "saved": false, "id": "cuoxq2t", "banned_at_utc": null, "mod_reason_title": null, "gilded": 0, "archived": true, "report_reasons": null, "author": "Pippafert", "can_mod_post": false, "send_replies": true, "parent_id": "t1_cuoxc2k", "score": 1, "approved_by": null, "downs": 0, "body": " Nancy, thank you so much. I am really lucky that despite all the really bad circumstances that happened in the past year I finally researched, found, and validated a PTSD diagnosis. I have just felt crazy for years, and every therapist I have met with has a diagnosis that does not seem to fit for me even though I try. When I finally, accidentally, traumatically fell into PTSD,  even though the circumstances were terrible, the outcome was so positive. I finally feel like I have  validity, I finally feel like I am not crazy.  I am in a much safer environment now. I reported my abuser last year and I spent six months in terror that he would come after me.   Now it's been almost a year and nothing has happened, legally or environmentally. I finally feel safe mostly going into my house   But the nine months before this work hell. I don't know how abused people live.   I reported a medical professional who could lose his job or have severe repercussions for the actions he took. I was not sure that he would  not take that outside of  A professional environment. That was part of the reason for reporting him. But it was not an intimate relationship, it was not a friendship.  I hope that the way that I have felt for the past nine months stays with me for the rest of my life, so I can understand and empathize with others who face the same situation.  It is inexplicable if you have not gone through it  and in comprehensible to most people if they have not experienced it.   I am so lucky that I have found a good PTSD therapist who really understands the condition. It's been a really long time  but if I had not had this last completely Trumatic experience I would not have found her. So I guess there is always a silver lining for everything even though I certainly would not have looked for this one. :-)   I don't know how my words could have possibly affected you when you have so much more to deal with and I do but thank you for responding and supporting.   There is no buck up, there is just Idil and those of us who do you can never express to someone who doesn't understand it with dealing means.  Thank you, stay strong, and keep posting. You helped me put my condition into perspective.", "edited": false, "author_flair_css_class": null, "collapsed": false, "is_submitter": false, "collapsed_reason": null, "body_html": "&lt;div class=\"md\"&gt;&lt;p&gt;Nancy, thank you so much. I am really lucky that despite all the really bad circumstances that happened in the past year I finally researched, found, and validated a PTSD diagnosis. I have just felt crazy for years, and every therapist I have met with has a diagnosis that does not seem to fit for me even though I try. When I finally, accidentally, traumatically fell into PTSD,  even though the circumstances were terrible, the outcome was so positive. I finally feel like I have  validity, I finally feel like I am not crazy.  I am in a much safer environment now. I reported my abuser last year and I spent six months in terror that he would come after me.   Now it&amp;#39;s been almost a year and nothing has happened, legally or environmentally. I finally feel safe mostly going into my house   But the nine months before this work hell. I don&amp;#39;t know how abused people live.   I reported a medical professional who could lose his job or have severe repercussions for the actions he took. I was not sure that he would  not take that outside of  A professional environment. That was part of the reason for reporting him. But it was not an intimate relationship, it was not a friendship.  I hope that the way that I have felt for the past nine months stays with me for the rest of my life, so I can understand and empathize with others who face the same situation.  It is inexplicable if you have not gone through it  and in comprehensible to most people if they have not experienced it.   I am so lucky that I have found a good PTSD therapist who really understands the condition. It&amp;#39;s been a really long time  but if I had not had this last completely Trumatic experience I would not have found her. So I guess there is always a silver lining for everything even though I certainly would not have looked for this one. :-)   I don&amp;#39;t know how my words could have possibly affected you when you have so much more to deal with and I do but thank you for responding and supporting.   There is no buck up, there is just Idil and those of us who do you can never express to someone who doesn&amp;#39;t understand it with dealing means.  Thank you, stay strong, and keep posting. You helped me put my condition into perspective.&lt;/p&gt;\n&lt;/div&gt;", "subreddit_type": "public", "can_gild": true, "subreddit": "ptsd", "name": "t1_cuoxq2t", "score_hidden": false, "permalink": "/r/ptsd/comments/3j5z9p/my_struggles_with_ptsd_depression_faith_and/cuoxq2t/", "num_reports": null, "stickied": false, "created": 1441280624.0, "author_flair_text": null, "created_utc": 1441251824.0, "subreddit_name_prefixed": "r/ptsd", "controversiality": 0, "depth": 2, "mod_reports": [], "mod_note": null, "distinguished": null}}, {"kind": "t1", "data": {"subreddit_id": "t5_2qm0x", "approved_at_utc": null, "ups": 1, "mod_reason_by": null, "banned_by": null, "removal_reason": null, "link_id": "t3_3j5z9p", "likes": null, "no_follow": true, "replies": {"kind": "Listing", "data": {"after": null, "whitelist_status": null, "modhash": "", "dist": null, "children": [{"kind": "t1", "data": {"subreddit_id": "t5_2qm0x", "approved_at_utc": null, "ups": 1, "mod_reason_by": null, "banned_by": null, "removal_reason": null, "link_id": "t3_3j5z9p", "likes": null, "no_follow": true, "replies": "", "user_reports": [], "saved": false, "id": "cupj7ku", "banned_at_utc": null, "mod_reason_title": null, "gilded": 0, "archived": true, "report_reasons": null, "author": "inmercyrejoice", "can_mod_post": false, "send_replies": true, "parent_id": "t1_cuoxq2k", "score": 1, "approved_by": null, "downs": 0, "body": "I'm so happy you found a good therapist. I've had three who admitted they were not sure how to help me. As I mentioned (or I think I did), writing is my outlet and helping others is my passion. Once again, you've humbled me and encouraged me. Life is all about perspective, but regardless, suffering is suffering no matter what causes it - a bad marriage, toothache, loss of a loved one, broken bone, migraine, betrayal - there are no comparisons between suffering or the capacity one has to endure a suffering. Bless you. Thank you for baring your heart to me. ", "edited": false, "author_flair_css_class": null, "collapsed": false, "is_submitter": true, "collapsed_reason": null, "body_html": "&lt;div class=\"md\"&gt;&lt;p&gt;I&amp;#39;m so happy you found a good therapist. I&amp;#39;ve had three who admitted they were not sure how to help me. As I mentioned (or I think I did), writing is my outlet and helping others is my passion. Once again, you&amp;#39;ve humbled me and encouraged me. Life is all about perspective, but regardless, suffering is suffering no matter what causes it - a bad marriage, toothache, loss of a loved one, broken bone, migraine, betrayal - there are no comparisons between suffering or the capacity one has to endure a suffering. Bless you. Thank you for baring your heart to me. &lt;/p&gt;\n&lt;/div&gt;", "subreddit_type": "public", "can_gild": true, "subreddit": "ptsd", "name": "t1_cupj7ku", "score_hidden": false, "permalink": "/r/ptsd/comments/3j5z9p/my_struggles_with_ptsd_depression_faith_and/cupj7ku/", "num_reports": null, "stickied": false, "created": 1441334196.0, "author_flair_text": null, "created_utc": 1441305396.0, "subreddit_name_prefixed": "r/ptsd", "controversiality": 0, "depth": 3, "mod_reports": [], "mod_note": null, "distinguished": null}}], "before": null}}, "user_reports": [], "saved": false, "id": "cuoxq2k", "banned_at_utc": null, "mod_reason_title": null, "gilded": 0, "archived": true, "report_reasons": null, "author": "Pippafert", "can_mod_post": false, "send_replies": true, "parent_id": "t1_cuoxc2k", "score": 1, "approved_by": null, "downs": 0, "body": " Nancy, thank you so much. I am really lucky that despite all the really bad circumstances that happened in the past year I finally researched, found, and validated a PTSD diagnosis. I have just felt crazy for years, and every therapist I have met with has a diagnosis that does not seem to fit for me even though I try. When I finally, accidentally, traumatically fell into PTSD,  even though the circumstances were terrible, the outcome was so positive. I finally feel like I have  validity, I finally feel like I am not crazy.  I am in a much safer environment now. I reported my abuser last year and I spent six months in terror that he would come after me.   Now it's been almost a year and nothing has happened, legally or environmentally. I finally feel safe mostly going into my house   But the nine months before this work hell. I don't know how abused people live.   I reported a medical professional who could lose his job or have severe repercussions for the actions he took. I was not sure that he would  not take that outside of  A professional environment. That was part of the reason for reporting him. But it was not an intimate relationship, it was not a friendship.  I hope that the way that I have felt for the past nine months stays with me for the rest of my life, so I can understand and empathize with others who face the same situation.  It is inexplicable if you have not gone through it  and in comprehensible to most people if they have not experienced it.   I am so lucky that I have found a good PTSD therapist who really understands the condition. It's been a really long time  but if I had not had this last completely Trumatic experience I would not have found her. So I guess there is always a silver lining for everything even though I certainly would not have looked for this one. :-)   I don't know how my words could have possibly affected you when you have so much more to deal with and I do but thank you for responding and supporting.   There is no buck up, there is just Idil and those of us who do you can never express to someone who doesn't understand it with dealing means.  Thank you, stay strong, and keep posting. You helped me put my condition into perspective.", "edited": false, "author_flair_css_class": null, "collapsed": false, "is_submitter": false, "collapsed_reason": null, "body_html": "&lt;div class=\"md\"&gt;&lt;p&gt;Nancy, thank you so much. I am really lucky that despite all the really bad circumstances that happened in the past year I finally researched, found, and validated a PTSD diagnosis. I have just felt crazy for years, and every therapist I have met with has a diagnosis that does not seem to fit for me even though I try. When I finally, accidentally, traumatically fell into PTSD,  even though the circumstances were terrible, the outcome was so positive. I finally feel like I have  validity, I finally feel like I am not crazy.  I am in a much safer environment now. I reported my abuser last year and I spent six months in terror that he would come after me.   Now it&amp;#39;s been almost a year and nothing has happened, legally or environmentally. I finally feel safe mostly going into my house   But the nine months before this work hell. I don&amp;#39;t know how abused people live.   I reported a medical professional who could lose his job or have severe repercussions for the actions he took. I was not sure that he would  not take that outside of  A professional environment. That was part of the reason for reporting him. But it was not an intimate relationship, it was not a friendship.  I hope that the way that I have felt for the past nine months stays with me for the rest of my life, so I can understand and empathize with others who face the same situation.  It is inexplicable if you have not gone through it  and in comprehensible to most people if they have not experienced it.   I am so lucky that I have found a good PTSD therapist who really understands the condition. It&amp;#39;s been a really long time  but if I had not had this last completely Trumatic experience I would not have found her. So I guess there is always a silver lining for everything even though I certainly would not have looked for this one. :-)   I don&amp;#39;t know how my words could have possibly affected you when you have so much more to deal with and I do but thank you for responding and supporting.   There is no buck up, there is just Idil and those of us who do you can never express to someone who doesn&amp;#39;t understand it with dealing means.  Thank you, stay strong, and keep posting. You helped me put my condition into perspective.&lt;/p&gt;\n&lt;/div&gt;", "subreddit_type": "public", "can_gild": true, "subreddit": "ptsd", "name": "t1_cuoxq2k", "score_hidden": false, "permalink": "/r/ptsd/comments/3j5z9p/my_struggles_with_ptsd_depression_faith_and/cuoxq2k/", "num_reports": null, "stickied": false, "created": 1441280624.0, "author_flair_text": null, "created_utc": 1441251824.0, "subreddit_name_prefixed": "r/ptsd", "controversiality": 0, "depth": 2, "mod_reports": [], "mod_note": null, "distinguished": null}}], "before": null}}, "user_reports": [], "saved": false, "id": "cuoxc2k", "banned_at_utc": null, "mod_reason_title": null, "gilded": 0, "archived": true, "report_reasons": null, "author": "inmercyrejoice", "can_mod_post": false, "send_replies": true, "parent_id": "t1_cumlbvq", "score": 1, "approved_by": null, "downs": 0, "body": "You words brought tears to my eyes. I'm so sorry for what you have and are going through. PTSD is a serious condition that many don't understand. They think that those of us that suffer with it should just \"buck up\" as the old saying goes. I hope you are living in a safe environment now or that you are able to find one. Stay strong, never give up hope. If there is anything I can do for you with in my power, let me know. \n\nThank you again for your encouraging words. blessings, Nancy", "edited": false, "author_flair_css_class": null, "collapsed": false, "is_submitter": true, "collapsed_reason": null, "body_html": "&lt;div class=\"md\"&gt;&lt;p&gt;You words brought tears to my eyes. I&amp;#39;m so sorry for what you have and are going through. PTSD is a serious condition that many don&amp;#39;t understand. They think that those of us that suffer with it should just &amp;quot;buck up&amp;quot; as the old saying goes. I hope you are living in a safe environment now or that you are able to find one. Stay strong, never give up hope. If there is anything I can do for you with in my power, let me know. &lt;/p&gt;\n\n&lt;p&gt;Thank you again for your encouraging words. blessings, Nancy&lt;/p&gt;\n&lt;/div&gt;", "subreddit_type": "public", "can_gild": true, "subreddit": "ptsd", "name": "t1_cuoxc2k", "score_hidden": false, "permalink": "/r/ptsd/comments/3j5z9p/my_struggles_with_ptsd_depression_faith_and/cuoxc2k/", "num_reports": null, "stickied": false, "created": 1441279847.0, "author_flair_text": null, "created_utc": 1441251047.0, "subreddit_name_prefixed": "r/ptsd", "controversiality": 0, "depth": 1, "mod_reports": [], "mod_note": null, "distinguished": null}}], "before": null}}, "user_reports": [], "saved": false, "id": "cumlbvq", "banned_at_utc": null, "mod_reason_title": null, "gilded": 0, "archived": true, "report_reasons": null, "author": "Pippafert", "can_mod_post": false, "send_replies": true, "parent_id": "t3_3j5z9p", "score": 2, "approved_by": null, "downs": 0, "body": " You are amazing. I suffer from PTSD but nothing compared to your story.  Recently, within the last year,  due to specific circumstances, I have been afraid to walk across the parking lot, or open my door, or go into my apartment alone, because of my most recent abuser. And my limbs are fully functional. I can't even imagine the strength it takes to continue when you have a fear is you do and a handicap as you have but still carry on.\n\n Your story is an inspiration. I think about my own fears and they are justified and real but at least I feel I can try to defend myself, even though I know I would lose. But I still can have this belief that it can be possible. Your story, after reading, makes me feel  so humble. I have survived his last nine months thinking that I will go out fighting. I don't even know what I would think in your situation. Thank you for helping some of us understand that always life can be more difficult and more challenging and require more bravery than what we are giving it right now. Honestly, I don't know what to say. I'm so sorry for your circumstances and I am so humbled by your post. Continue on burning your candle and bringing light to those of us who don't see a way out.", "edited": false, "author_flair_css_class": null, "collapsed": false, "is_submitter": false, "collapsed_reason": null, "body_html": "&lt;div class=\"md\"&gt;&lt;p&gt;You are amazing. I suffer from PTSD but nothing compared to your story.  Recently, within the last year,  due to specific circumstances, I have been afraid to walk across the parking lot, or open my door, or go into my apartment alone, because of my most recent abuser. And my limbs are fully functional. I can&amp;#39;t even imagine the strength it takes to continue when you have a fear is you do and a handicap as you have but still carry on.&lt;/p&gt;\n\n&lt;p&gt;Your story is an inspiration. I think about my own fears and they are justified and real but at least I feel I can try to defend myself, even though I know I would lose. But I still can have this belief that it can be possible. Your story, after reading, makes me feel  so humble. I have survived his last nine months thinking that I will go out fighting. I don&amp;#39;t even know what I would think in your situation. Thank you for helping some of us understand that always life can be more difficult and more challenging and require more bravery than what we are giving it right now. Honestly, I don&amp;#39;t know what to say. I&amp;#39;m so sorry for your circumstances and I am so humbled by your post. Continue on burning your candle and bringing light to those of us who don&amp;#39;t see a way out.&lt;/p&gt;\n&lt;/div&gt;", "subreddit_type": "public", "can_gild": true, "subreddit": "ptsd", "name": "t1_cumlbvq", "score_hidden": false, "permalink": "/r/ptsd/comments/3j5z9p/my_struggles_with_ptsd_depression_faith_and/cumlbvq/", "num_reports": null, "stickied": false, "created": 1441103101.0, "author_flair_text": null, "created_utc": 1441074301.0, "subreddit_name_prefixed": "r/ptsd", "controversiality": 0, "depth": 0, "mod_reports": [], "mod_note": null, "distinguished": null}}], "before": null}}]