[{"kind": "Listing", "data": {"after": null, "whitelist_status": "all_ads", "modhash": "", "dist": 1, "children": [{"kind": "t3", "data": {"is_crosspostable": false, "subreddit_id": "t5_2qh33", "approved_at_utc": null, "mod_reason_by": null, "banned_by": null, "removal_reason": null, "thumbnail_width": 140, "subreddit": "funny", "selftext_html": null, "selftext": "", "likes": null, "suggested_sort": null, "mod_note": null, "user_reports": [], "secure_media": null, "is_reddit_media_domain": false, "saved": false, "id": "2qyhov", "banned_at_utc": null, "mod_reason_title": null, "view_count": null, "archived": true, "clicked": false, "no_follow": true, "author": "onijin", "num_crossposts": 0, "link_flair_text": null, "can_mod_post": false, "send_replies": true, "pinned": false, "score": 2, "approved_by": null, "over_18": false, "domain": "i.imgur.com", "hidden": false, "num_comments": 13, "thumbnail": "https://b.thumbs.redditmedia.com/iYC28NojvP5YdhI6JhMProoFy2aI2o4wU2WZfmaxamY.jpg", "hide_score": false, "edited": false, "link_flair_css_class": null, "author_flair_css_class": null, "contest_mode": false, "gilded": 0, "locked": false, "downs": 0, "brand_safe": true, "subreddit_subscribers": 19139914, "secure_media_embed": {}, "media_embed": {}, "stickied": false, "can_gild": false, "thumbnail_height": 83, "parent_whitelist_status": "all_ads", "name": "t3_2qyhov", "spoiler": false, "permalink": "/r/funny/comments/2qyhov/egg_nog_my_old_friend_its_been_a_good_run_ill_see/", "subreddit_type": "public", "whitelist_status": "all_ads", "report_reasons": null, "created": 1420092679.0, "url": "http://i.imgur.com/7wgqi55.jpg", "author_flair_text": null, "quarantine": false, "title": "Egg nog my old friend, it's been a good run. I'll see you again next year.", "created_utc": 1420063879.0, "subreddit_name_prefixed": "r/funny", "distinguished": null, "media": null, "upvote_ratio": 0.6, "mod_reports": [], "is_self": false, "visited": false, "num_reports": null, "is_video": false, "ups": 2}}], "before": null}}, {"kind": "Listing", "data": {"after": null, "whitelist_status": "all_ads", "modhash": "", "dist": null, "children": [{"kind": "t1", "data": {"subreddit_id": "t5_2qh33", "approved_at_utc": null, "ups": 1, "mod_reason_by": null, "banned_by": null, "removal_reason": null, "link_id": "t3_2qyhov", "likes": null, "no_follow": true, "replies": "", "user_reports": [], "saved": false, "id": "cnapa8v", "banned_at_utc": null, "mod_reason_title": null, "gilded": 0, "archived": true, "report_reasons": null, "author": "every1wins", "can_mod_post": false, "send_replies": true, "parent_id": "t3_2qyhov", "score": 1, "approved_by": null, "downs": 0, "body": "I still dream of the taste of real milk.", "edited": false, "author_flair_css_class": null, "collapsed": false, "is_submitter": false, "collapsed_reason": null, "body_html": "&lt;div class=\"md\"&gt;&lt;p&gt;I still dream of the taste of real milk.&lt;/p&gt;\n&lt;/div&gt;", "subreddit_type": "public", "can_gild": true, "subreddit": "funny", "name": "t1_cnapa8v", "score_hidden": false, "permalink": "/r/funny/comments/2qyhov/egg_nog_my_old_friend_its_been_a_good_run_ill_see/cnapa8v/", "num_reports": null, "stickied": false, "created": 1420092799.0, "author_flair_text": null, "created_utc": 1420063999.0, "subreddit_name_prefixed": "r/funny", "controversiality": 0, "depth": 0, "mod_reports": [], "mod_note": null, "distinguished": null}}, {"kind": "t1", "data": {"subreddit_id": "t5_2qh33", "approved_at_utc": null, "ups": 1, "mod_reason_by": null, "banned_by": null, "removal_reason": null, "link_id": "t3_2qyhov", "likes": null, "no_follow": true, "replies": {"kind": "Listing", "data": {"after": null, "whitelist_status": "all_ads", "modhash": "", "dist": null, "children": [{"kind": "t1", "data": {"subreddit_id": "t5_2qh33", "approved_at_utc": null, "ups": 2, "mod_reason_by": null, "banned_by": null, "removal_reason": null, "link_id": "t3_2qyhov", "likes": null, "no_follow": true, "replies": {"kind": "Listing", "data": {"after": null, "whitelist_status": "all_ads", "modhash": "", "dist": null, "children": [{"kind": "t1", "data": {"subreddit_id": "t5_2qh33", "approved_at_utc": null, "ups": 1, "mod_reason_by": null, "banned_by": null, "removal_reason": null, "link_id": "t3_2qyhov", "likes": null, "no_follow": true, "replies": "", "user_reports": [], "saved": false, "id": "cnarjl3", "banned_at_utc": null, "mod_reason_title": null, "gilded": 0, "archived": true, "report_reasons": null, "author": "_generic_name_here", "can_mod_post": false, "send_replies": true, "parent_id": "t1_cnaqdb1", "score": 1, "approved_by": null, "downs": 0, "body": "I see what you did there. cute. There are also recipes.", "edited": false, "author_flair_css_class": null, "collapsed": false, "is_submitter": false, "collapsed_reason": null, "body_html": "&lt;div class=\"md\"&gt;&lt;p&gt;I see what you did there. cute. There are also recipes.&lt;/p&gt;\n&lt;/div&gt;", "subreddit_type": "public", "can_gild": true, "subreddit": "funny", "name": "t1_cnarjl3", "score_hidden": false, "permalink": "/r/funny/comments/2qyhov/egg_nog_my_old_friend_its_been_a_good_run_ill_see/cnarjl3/", "num_reports": null, "stickied": false, "created": 1420097636.0, "author_flair_text": null, "created_utc": 1420068836.0, "subreddit_name_prefixed": "r/funny", "controversiality": 0, "depth": 2, "mod_reports": [], "mod_note": null, "distinguished": null}}], "before": null}}, "user_reports": [], "saved": false, "id": "cnaqdb1", "banned_at_utc": null, "mod_reason_title": null, "gilded": 0, "archived": true, "report_reasons": null, "author": "onijin", "can_mod_post": false, "send_replies": true, "parent_id": "t1_cnapokf", "score": 2, "approved_by": null, "downs": 0, "body": "In my corner of the world, after Jan 1 it's liquid unobtanium.", "edited": false, "author_flair_css_class": null, "collapsed": false, "is_submitter": true, "collapsed_reason": null, "body_html": "&lt;div class=\"md\"&gt;&lt;p&gt;In my corner of the world, after Jan 1 it&amp;#39;s liquid unobtanium.&lt;/p&gt;\n&lt;/div&gt;", "subreddit_type": "public", "can_gild": true, "subreddit": "funny", "name": "t1_cnaqdb1", "score_hidden": false, "permalink": "/r/funny/comments/2qyhov/egg_nog_my_old_friend_its_been_a_good_run_ill_see/cnaqdb1/", "num_reports": null, "stickied": false, "created": 1420095101.0, "author_flair_text": null, "created_utc": 1420066301.0, "subreddit_name_prefixed": "r/funny", "controversiality": 0, "depth": 1, "mod_reports": [], "mod_note": null, "distinguished": null}}], "before": null}}, "user_reports": [], "saved": false, "id": "cnapokf", "banned_at_utc": null, "mod_reason_title": null, "gilded": 0, "archived": true, "report_reasons": null, "author": "_generic_name_here", "can_mod_post": false, "send_replies": true, "parent_id": "t3_2qyhov", "score": 1, "approved_by": null, "downs": 0, "body": "You can literally drink it year round. There is nothing preventing you from getting more.", "edited": false, "author_flair_css_class": null, "collapsed": false, "is_submitter": false, "collapsed_reason": null, "body_html": "&lt;div class=\"md\"&gt;&lt;p&gt;You can literally drink it year round. There is nothing preventing you from getting more.&lt;/p&gt;\n&lt;/div&gt;", "subreddit_type": "public", "can_gild": true, "subreddit": "funny", "name": "t1_cnapokf", "score_hidden": false, "permalink": "/r/funny/comments/2qyhov/egg_nog_my_old_friend_its_been_a_good_run_ill_see/cnapokf/", "num_reports": null, "stickied": false, "created": 1420093643.0, "author_flair_text": null, "created_utc": 1420064843.0, "subreddit_name_prefixed": "r/funny", "controversiality": 0, "depth": 0, "mod_reports": [], "mod_note": null, "distinguished": null}}, {"kind": "t1", "data": {"subreddit_id": "t5_2qh33", "approved_at_utc": null, "ups": 1, "mod_reason_by": null, "banned_by": null, "removal_reason": null, "link_id": "t3_2qyhov", "likes": null, "no_follow": true, "replies": {"kind": "Listing", "data": {"after": null, "whitelist_status": "all_ads", "modhash": "", "dist": null, "children": [{"kind": "t1", "data": {"subreddit_id": "t5_2qh33", "approved_at_utc": null, "ups": 1, "mod_reason_by": null, "banned_by": null, "removal_reason": null, "link_id": "t3_2qyhov", "likes": null, "no_follow": true, "replies": {"kind": "Listing", "data": {"after": null, "whitelist_status": "all_ads", "modhash": "", "dist": null, "children": [{"kind": "t1", "data": {"subreddit_id": "t5_2qh33", "approved_at_utc": null, "ups": 1, "mod_reason_by": null, "banned_by": null, "removal_reason": null, "link_id": "t3_2qyhov", "likes": null, "no_follow": true, "replies": {"kind": "Listing", "data": {"after": null, "whitelist_status": "all_ads", "modhash": "", "dist": null, "children": [{"kind": "t1", "data": {"subreddit_id": "t5_2qh33", "approved_at_utc": null, "ups": 1, "mod_reason_by": null, "banned_by": null, "removal_reason": null, "link_id": "t3_2qyhov", "likes": null, "no_follow": true, "replies": {"kind": "Listing", "data": {"after": null, "whitelist_status": "all_ads", "modhash": "", "dist": null, "children": [{"kind": "t1", "data": {"subreddit_id": "t5_2qh33", "approved_at_utc": null, "ups": 1, "mod_reason_by": null, "banned_by": null, "removal_reason": null, "link_id": "t3_2qyhov", "likes": null, "no_follow": true, "replies": {"kind": "Listing", "data": {"after": null, "whitelist_status": "all_ads", "modhash": "", "dist": null, "children": [{"kind": "t1", "data": {"subreddit_id": "t5_2qh33", "approved_at_utc": null, "ups": 1, "mod_reason_by": null, "banned_by": null, "removal_reason": null, "link_id": "t3_2qyhov", "likes": null, "no_follow": true, "replies": {"kind": "Listing", "data": {"after": null, "whitelist_status": "all_ads", "modhash": "", "dist": null, "children": [{"kind": "t1", "data": {"subreddit_id": "t5_2qh33", "approved_at_utc": null, "ups": 1, "mod_reason_by": null, "banned_by": null, "removal_reason": null, "link_id": "t3_2qyhov", "likes": null, "no_follow": true, "replies": {"kind": "Listing", "data": {"after": null, "whitelist_status": "all_ads", "modhash": "", "dist": null, "children": [{"kind": "t1", "data": {"subreddit_id": "t5_2qh33", "approved_at_utc": null, "ups": 1, "mod_reason_by": null, "banned_by": null, "removal_reason": null, "link_id": "t3_2qyhov", "likes": null, "no_follow": true, "replies": "", "user_reports": [], "saved": false, "id": "cnaszmc", "banned_at_utc": null, "mod_reason_title": null, "gilded": 0, "archived": true, "report_reasons": null, "author": "onijin", "can_mod_post": false, "send_replies": true, "parent_id": "t1_cnasyii", "score": 1, "approved_by": null, "downs": 0, "body": "With whiskey I prefer it cold with bushmills. ", "edited": false, "author_flair_css_class": null, "collapsed": false, "is_submitter": true, "collapsed_reason": null, "body_html": "&lt;div class=\"md\"&gt;&lt;p&gt;With whiskey I prefer it cold with bushmills. &lt;/p&gt;\n&lt;/div&gt;", "subreddit_type": "public", "can_gild": true, "subreddit": "funny", "name": "t1_cnaszmc", "score_hidden": false, "permalink": "/r/funny/comments/2qyhov/egg_nog_my_old_friend_its_been_a_good_run_ill_see/cnaszmc/", "num_reports": null, "stickied": false, "created": 1420100868.0, "author_flair_text": null, "created_utc": 1420072068.0, "subreddit_name_prefixed": "r/funny", "controversiality": 0, "depth": 7, "mod_reports": [], "mod_note": null, "distinguished": null}}], "before": null}}, "user_reports": [], "saved": false, "id": "cnasyii", "banned_at_utc": null, "mod_reason_title": null, "gilded": 0, "archived": true, "report_reasons": null, "author": "Theo-greking", "can_mod_post": false, "send_replies": true, "parent_id": "t1_cnaswto", "score": 1, "approved_by": null, "downs": 0, "body": "I like it with whiskey myself used almost an entire bottle of seagrams in mine this year.  Almost enough to put people to sleep ", "edited": false, "author_flair_css_class": null, "collapsed": false, "is_submitter": false, "collapsed_reason": null, "body_html": "&lt;div class=\"md\"&gt;&lt;p&gt;I like it with whiskey myself used almost an entire bottle of seagrams in mine this year.  Almost enough to put people to sleep &lt;/p&gt;\n&lt;/div&gt;", "subreddit_type": "public", "can_gild": true, "subreddit": "funny", "name": "t1_cnasyii", "score_hidden": false, "permalink": "/r/funny/comments/2qyhov/egg_nog_my_old_friend_its_been_a_good_run_ill_see/cnasyii/", "num_reports": null, "stickied": false, "created": 1420100802.0, "author_flair_text": null, "created_utc": 1420072002.0, "subreddit_name_prefixed": "r/funny", "controversiality": 0, "depth": 6, "mod_reports": [], "mod_note": null, "distinguished": null}}], "before": null}}, "user_reports": [], "saved": false, "id": "cnaswto", "banned_at_utc": null, "mod_reason_title": null, "gilded": 0, "archived": true, "report_reasons": null, "author": "onijin", "can_mod_post": false, "send_replies": true, "parent_id": "t1_cnasmmg", "score": 1, "approved_by": null, "downs": 0, "body": "Yes. I like it hot with rum. ", "edited": false, "author_flair_css_class": null, "collapsed": false, "is_submitter": true, "collapsed_reason": null, "body_html": "&lt;div class=\"md\"&gt;&lt;p&gt;Yes. I like it hot with rum. &lt;/p&gt;\n&lt;/div&gt;", "subreddit_type": "public", "can_gild": true, "subreddit": "funny", "name": "t1_cnaswto", "score_hidden": false, "permalink": "/r/funny/comments/2qyhov/egg_nog_my_old_friend_its_been_a_good_run_ill_see/cnaswto/", "num_reports": null, "stickied": false, "created": 1420100702.0, "author_flair_text": null, "created_utc": 1420071902.0, "subreddit_name_prefixed": "r/funny", "controversiality": 0, "depth": 5, "mod_reports": [], "mod_note": null, "distinguished": null}}], "before": null}}, "user_reports": [], "saved": false, "id": "cnasmmg", "banned_at_utc": null, "mod_reason_title": null, "gilded": 0, "archived": true, "report_reasons": null, "author": "Theo-greking", "can_mod_post": false, "send_replies": true, "parent_id": "t1_cnargaq", "score": 1, "approved_by": null, "downs": 0, "body": "Do you drink it hot ? ", "edited": false, "author_flair_css_class": null, "collapsed": false, "is_submitter": false, "collapsed_reason": null, "body_html": "&lt;div class=\"md\"&gt;&lt;p&gt;Do you drink it hot ? &lt;/p&gt;\n&lt;/div&gt;", "subreddit_type": "public", "can_gild": true, "subreddit": "funny", "name": "t1_cnasmmg", "score_hidden": false, "permalink": "/r/funny/comments/2qyhov/egg_nog_my_old_friend_its_been_a_good_run_ill_see/cnasmmg/", "num_reports": null, "stickied": false, "created": 1420100062.0, "author_flair_text": null, "created_utc": 1420071262.0, "subreddit_name_prefixed": "r/funny", "controversiality": 0, "depth": 4, "mod_reports": [], "mod_note": null, "distinguished": null}}], "before": null}}, "user_reports": [], "saved": false, "id": "cnargaq", "banned_at_utc": null, "mod_reason_title": null, "gilded": 0, "archived": true, "report_reasons": null, "author": "onijin", "can_mod_post": false, "send_replies": true, "parent_id": "t1_cnaqx81", "score": 1, "approved_by": null, "downs": 0, "body": "Either way I freaking love it. Doubly so loaded with booze.", "edited": false, "author_flair_css_class": null, "collapsed": false, "is_submitter": true, "collapsed_reason": null, "body_html": "&lt;div class=\"md\"&gt;&lt;p&gt;Either way I freaking love it. Doubly so loaded with booze.&lt;/p&gt;\n&lt;/div&gt;", "subreddit_type": "public", "can_gild": true, "subreddit": "funny", "name": "t1_cnargaq", "score_hidden": false, "permalink": "/r/funny/comments/2qyhov/egg_nog_my_old_friend_its_been_a_good_run_ill_see/cnargaq/", "num_reports": null, "stickied": false, "created": 1420097443.0, "author_flair_text": null, "created_utc": 1420068643.0, "subreddit_name_prefixed": "r/funny", "controversiality": 0, "depth": 3, "mod_reports": [], "mod_note": null, "distinguished": null}}], "before": null}}, "user_reports": [], "saved": false, "id": "cnaqx81", "banned_at_utc": null, "mod_reason_title": null, "gilded": 0, "archived": true, "report_reasons": null, "author": "Theo-greking", "can_mod_post": false, "send_replies": true, "parent_id": "t1_cnaqdg0", "score": 1, "approved_by": null, "downs": 0, "body": "You do at least know it's a hot beverage right ", "edited": false, "author_flair_css_class": null, "collapsed": false, "is_submitter": false, "collapsed_reason": null, "body_html": "&lt;div class=\"md\"&gt;&lt;p&gt;You do at least know it&amp;#39;s a hot beverage right &lt;/p&gt;\n&lt;/div&gt;", "subreddit_type": "public", "can_gild": true, "subreddit": "funny", "name": "t1_cnaqx81", "score_hidden": false, "permalink": "/r/funny/comments/2qyhov/egg_nog_my_old_friend_its_been_a_good_run_ill_see/cnaqx81/", "num_reports": null, "stickied": false, "created": 1420096329.0, "author_flair_text": null, "created_utc": 1420067529.0, "subreddit_name_prefixed": "r/funny", "controversiality": 0, "depth": 2, "mod_reports": [], "mod_note": null, "distinguished": null}}], "before": null}}, "user_reports": [], "saved": false, "id": "cnaqdg0", "banned_at_utc": null, "mod_reason_title": null, "gilded": 0, "archived": true, "report_reasons": null, "author": "onijin", "can_mod_post": false, "send_replies": true, "parent_id": "t1_cnaptvw", "score": 1, "approved_by": null, "downs": 0, "body": "Yes, yes I do.", "edited": false, "author_flair_css_class": null, "collapsed": false, "is_submitter": true, "collapsed_reason": null, "body_html": "&lt;div class=\"md\"&gt;&lt;p&gt;Yes, yes I do.&lt;/p&gt;\n&lt;/div&gt;", "subreddit_type": "public", "can_gild": true, "subreddit": "funny", "name": "t1_cnaqdg0", "score_hidden": false, "permalink": "/r/funny/comments/2qyhov/egg_nog_my_old_friend_its_been_a_good_run_ill_see/cnaqdg0/", "num_reports": null, "stickied": false, "created": 1420095110.0, "author_flair_text": null, "created_utc": 1420066310.0, "subreddit_name_prefixed": "r/funny", "controversiality": 0, "depth": 1, "mod_reports": [], "mod_note": null, "distinguished": null}}], "before": null}}, "user_reports": [], "saved": false, "id": "cnaptvw", "banned_at_utc": null, "mod_reason_title": null, "gilded": 0, "archived": true, "report_reasons": null, "author": "Theo-greking", "can_mod_post": false, "send_replies": true, "parent_id": "t3_2qyhov", "score": 1, "approved_by": null, "downs": 0, "body": "People actually drink that swill it's like custard ", "edited": false, "author_flair_css_class": null, "collapsed": false, "is_submitter": false, "collapsed_reason": null, "body_html": "&lt;div class=\"md\"&gt;&lt;p&gt;People actually drink that swill it&amp;#39;s like custard &lt;/p&gt;\n&lt;/div&gt;", "subreddit_type": "public", "can_gild": true, "subreddit": "funny", "name": "t1_cnaptvw", "score_hidden": false, "permalink": "/r/funny/comments/2qyhov/egg_nog_my_old_friend_its_been_a_good_run_ill_see/cnaptvw/", "num_reports": null, "stickied": false, "created": 1420093953.0, "author_flair_text": null, "created_utc": 1420065153.0, "subreddit_name_prefixed": "r/funny", "controversiality": 0, "depth": 0, "mod_reports": [], "mod_note": null, "distinguished": null}}, {"kind": "t1", "data": {"subreddit_id": "t5_2qh33", "approved_at_utc": null, "ups": 1, "mod_reason_by": null, "banned_by": null, "removal_reason": null, "link_id": "t3_2qyhov", "likes": null, "no_follow": true, "replies": "", "user_reports": [], "saved": false, "id": "cnarg7a", "banned_at_utc": null, "mod_reason_title": null, "gilded": 0, "archived": true, "report_reasons": null, "author": "heatmakerr", "can_mod_post": false, "send_replies": true, "parent_id": "t3_2qyhov", "score": 1, "approved_by": null, "downs": 0, "body": "its still good!..its still good!", "edited": false, "author_flair_css_class": null, "collapsed": false, "is_submitter": false, "collapsed_reason": null, "body_html": "&lt;div class=\"md\"&gt;&lt;p&gt;its still good!..its still good!&lt;/p&gt;\n&lt;/div&gt;", "subreddit_type": "public", "can_gild": true, "subreddit": "funny", "name": "t1_cnarg7a", "score_hidden": false, "permalink": "/r/funny/comments/2qyhov/egg_nog_my_old_friend_its_been_a_good_run_ill_see/cnarg7a/", "num_reports": null, "stickied": false, "created": 1420097436.0, "author_flair_text": null, "created_utc": 1420068636.0, "subreddit_name_prefixed": "r/funny", "controversiality": 0, "depth": 0, "mod_reports": [], "mod_note": null, "distinguished": null}}], "before": null}}]