[{"kind": "Listing", "data": {"after": null, "whitelist_status": null, "modhash": "", "dist": 1, "children": [{"kind": "t3", "data": {"is_crosspostable": false, "subreddit_id": "t5_2qm0x", "approved_at_utc": null, "mod_reason_by": null, "banned_by": null, "removal_reason": null, "subreddit": "ptsd", "selftext_html": "&lt;!-- SC_OFF --&gt;&lt;div class=\"md\"&gt;&lt;p&gt;Let me begin by saying hello and my name is Joshua.&lt;/p&gt;\n\n&lt;p&gt;For about 22 years I was physically, mentally, and sexually abused until last summer when I took a stand for myself against my drug-addled stepfather. He saw subsequently arrested for battery with intent to cause serious bodily harm. Before then my mom always talked me down from doing something. He put me through plate glass windows, hung me out the passenger seat of a car going sixty, unbuckled.&lt;/p&gt;\n\n&lt;p&gt;Those 22 years, I let it bottle up and it wasn&amp;#39;t until he was arrested that I realized that sleeping against the door frame feeling for movements could stop. But I couldn&amp;#39;t every truly be safe. This resulted in balling my eyes out over the good memories. This caused panic attacks when I saw a car that resembled his drive by, despite him being in jail at the time.&lt;/p&gt;\n\n&lt;p&gt;I started seeing a good therapist who gave me my diagnosis and she has been helping, from time to time I should say.&lt;/p&gt;\n\n&lt;p&gt;My psychologist has me on the following:\nBrintellix 20mg\nSeroquel XR 300mg\nAtivan 2mg&lt;/p&gt;\n\n&lt;p&gt;So now that you know all of that, I have my good days and I have my bad days. Here lately they&amp;#39;ve been more bad than good. In September he got out of jail for good time served and immediately broke the restraining order (my mom and I moved while he was in jail; I am my mom&amp;#39;s caretaker) trying to find us, and we weren&amp;#39;t there so he went away. However, that night my dog I have for 9 years was brutally killed while on his chain. And the police told me there wasn&amp;#39;t anything we could do as we lived in the country and it could have been a wild animal.&lt;/p&gt;\n\n&lt;p&gt;So that brings me to now. Anyone looked into a certified therapy dog. I fear my mother doesn&amp;#39;t have much time left and I don&amp;#39;t know what I&amp;#39;m going to do in my emotional state without something/someone to crying into. That and all my other medical problems make this so hard. My therapist asked me last week where I see myself in 3 years/3 months/3 days, and I didn&amp;#39;t have an answer. Right now, one foot in front of the other, one step at a time.&lt;/p&gt;\n\n&lt;p&gt;For the record, I do have flashbacks and nightmares. Sometimes I&amp;#39;ll get a day off but they are fairly common. Seroquel only helps so much for that.&lt;/p&gt;\n&lt;/div&gt;&lt;!-- SC_ON --&gt;", "selftext": "Let me begin by saying hello and my name is Joshua.\n\nFor about 22 years I was physically, mentally, and sexually abused until last summer when I took a stand for myself against my drug-addled stepfather. He saw subsequently arrested for battery with intent to cause serious bodily harm. Before then my mom always talked me down from doing something. He put me through plate glass windows, hung me out the passenger seat of a car going sixty, unbuckled.\n\nThose 22 years, I let it bottle up and it wasn't until he was arrested that I realized that sleeping against the door frame feeling for movements could stop. But I couldn't every truly be safe. This resulted in balling my eyes out over the good memories. This caused panic attacks when I saw a car that resembled his drive by, despite him being in jail at the time.\n\nI started seeing a good therapist who gave me my diagnosis and she has been helping, from time to time I should say.\n\nMy psychologist has me on the following:\nBrintellix 20mg\nSeroquel XR 300mg\nAtivan 2mg\n\nSo now that you know all of that, I have my good days and I have my bad days. Here lately they've been more bad than good. In September he got out of jail for good time served and immediately broke the restraining order (my mom and I moved while he was in jail; I am my mom's caretaker) trying to find us, and we weren't there so he went away. However, that night my dog I have for 9 years was brutally killed while on his chain. And the police told me there wasn't anything we could do as we lived in the country and it could have been a wild animal.\n\nSo that brings me to now. Anyone looked into a certified therapy dog. I fear my mother doesn't have much time left and I don't know what I'm going to do in my emotional state without something/someone to crying into. That and all my other medical problems make this so hard. My therapist asked me last week where I see myself in 3 years/3 months/3 days, and I didn't have an answer. Right now, one foot in front of the other, one step at a time.\n\nFor the record, I do have flashbacks and nightmares. Sometimes I'll get a day off but they are fairly common. Seroquel only helps so much for that.\n", "likes": null, "suggested_sort": "new", "mod_note": null, "user_reports": [], "secure_media": null, "is_reddit_media_domain": false, "saved": false, "id": "2qyrwp", "banned_at_utc": null, "mod_reason_title": null, "view_count": null, "archived": true, "clicked": false, "no_follow": true, "author": "jmattick", "num_crossposts": 0, "link_flair_text": null, "can_mod_post": false, "send_replies": true, "pinned": false, "score": 5, "approved_by": null, "over_18": false, "domain": "self.ptsd", "hidden": false, "num_comments": 11, "thumbnail": "", "hide_score": false, "edited": 1420070438.0, "link_flair_css_class": null, "author_flair_css_class": null, "contest_mode": false, "gilded": 0, "locked": false, "downs": 0, "brand_safe": false, "subreddit_subscribers": 13131, "secure_media_embed": {}, "media_embed": {}, "stickied": false, "can_gild": false, "is_self": true, "parent_whitelist_status": null, "name": "t3_2qyrwp", "spoiler": false, "permalink": "/r/ptsd/comments/2qyrwp/has_a_therapy_dog_helped_anyone_potential_tw/", "subreddit_type": "public", "whitelist_status": null, "report_reasons": null, "created": 1420098996.0, "url": "https://www.reddit.com/r/ptsd/comments/2qyrwp/has_a_therapy_dog_helped_anyone_potential_tw/", "author_flair_text": null, "quarantine": false, "title": "Has a therapy dog helped anyone? (Potential TW)", "created_utc": 1420070196.0, "subreddit_name_prefixed": "r/ptsd", "distinguished": null, "media": null, "upvote_ratio": 0.7, "mod_reports": [], "visited": false, "num_reports": null, "is_video": false, "ups": 5}}], "before": null}}, {"kind": "Listing", "data": {"after": null, "whitelist_status": null, "modhash": "", "dist": null, "children": [{"kind": "t1", "data": {"subreddit_id": "t5_2qm0x", "approved_at_utc": null, "ups": 1, "mod_reason_by": null, "banned_by": null, "removal_reason": null, "link_id": "t3_2qyrwp", "likes": null, "no_follow": true, "replies": "", "user_reports": [], "saved": false, "id": "cnr4iqp", "banned_at_utc": null, "mod_reason_title": null, "gilded": 0, "archived": true, "report_reasons": null, "author": "LittleBlueEyes", "can_mod_post": false, "send_replies": true, "parent_id": "t3_2qyrwp", "score": 1, "approved_by": null, "downs": 0, "body": "Do you mean a service dog, trained in tasks to assist a disabled person?\n\nA therapy dog comforts people in group settings, such as a school or nursing home.  \n\n", "edited": false, "author_flair_css_class": null, "collapsed": false, "is_submitter": false, "collapsed_reason": null, "body_html": "&lt;div class=\"md\"&gt;&lt;p&gt;Do you mean a service dog, trained in tasks to assist a disabled person?&lt;/p&gt;\n\n&lt;p&gt;A therapy dog comforts people in group settings, such as a school or nursing home.  &lt;/p&gt;\n&lt;/div&gt;", "subreddit_type": "public", "can_gild": true, "subreddit": "ptsd", "name": "t1_cnr4iqp", "score_hidden": false, "permalink": "/r/ptsd/comments/2qyrwp/has_a_therapy_dog_helped_anyone_potential_tw/cnr4iqp/", "num_reports": null, "stickied": false, "created": 1421461789.0, "author_flair_text": null, "created_utc": 1421432989.0, "subreddit_name_prefixed": "r/ptsd", "controversiality": 0, "depth": 0, "mod_reports": [], "mod_note": null, "distinguished": null}}, {"kind": "t1", "data": {"subreddit_id": "t5_2qm0x", "approved_at_utc": null, "ups": 2, "mod_reason_by": null, "banned_by": null, "removal_reason": null, "link_id": "t3_2qyrwp", "likes": null, "no_follow": true, "replies": "", "user_reports": [], "saved": false, "id": "cnb6jpa", "banned_at_utc": null, "mod_reason_title": null, "gilded": 0, "archived": true, "report_reasons": null, "author": "Crito", "can_mod_post": false, "send_replies": true, "parent_id": "t3_2qyrwp", "score": 2, "approved_by": null, "downs": 0, "body": "I have a German Shepherd. Though he is not trained as a therapy dog, I do sleep much easier now. Because he is alert, I don't have to be. (Obviously, I am, but not nearly as much so.)\n\nThat said, the situation you are in sounds very scary. I hope you have a way to protect yourself if he comes after you? If anything, I would think a dog *who lives inside* could be a great comfort to you, as well as a way to warn you if this man comes after you. Keep in mind that a dog without training is not going to protect you from an intruder. It is your job to protect the dog. The bark is only a warning and, hopefully, a deterrent. \n\nAgain, though, this needs to be an inside dog. Kibble should be kept inside as well. I would also monitor your dog's outdoor activity, as poisoning people's animals is unfortunately not an uncommon tactic for abusers. \n\nTake care of yourself. ", "edited": false, "author_flair_css_class": null, "collapsed": false, "is_submitter": false, "collapsed_reason": null, "body_html": "&lt;div class=\"md\"&gt;&lt;p&gt;I have a German Shepherd. Though he is not trained as a therapy dog, I do sleep much easier now. Because he is alert, I don&amp;#39;t have to be. (Obviously, I am, but not nearly as much so.)&lt;/p&gt;\n\n&lt;p&gt;That said, the situation you are in sounds very scary. I hope you have a way to protect yourself if he comes after you? If anything, I would think a dog &lt;em&gt;who lives inside&lt;/em&gt; could be a great comfort to you, as well as a way to warn you if this man comes after you. Keep in mind that a dog without training is not going to protect you from an intruder. It is your job to protect the dog. The bark is only a warning and, hopefully, a deterrent. &lt;/p&gt;\n\n&lt;p&gt;Again, though, this needs to be an inside dog. Kibble should be kept inside as well. I would also monitor your dog&amp;#39;s outdoor activity, as poisoning people&amp;#39;s animals is unfortunately not an uncommon tactic for abusers. &lt;/p&gt;\n\n&lt;p&gt;Take care of yourself. &lt;/p&gt;\n&lt;/div&gt;", "subreddit_type": "public", "can_gild": true, "subreddit": "ptsd", "name": "t1_cnb6jpa", "score_hidden": false, "permalink": "/r/ptsd/comments/2qyrwp/has_a_therapy_dog_helped_anyone_potential_tw/cnb6jpa/", "num_reports": null, "stickied": false, "created": 1420151412.0, "author_flair_text": null, "created_utc": 1420122612.0, "subreddit_name_prefixed": "r/ptsd", "controversiality": 0, "depth": 0, "mod_reports": [], "mod_note": null, "distinguished": null}}, {"kind": "t1", "data": {"subreddit_id": "t5_2qm0x", "approved_at_utc": null, "ups": 7, "mod_reason_by": null, "banned_by": null, "removal_reason": null, "link_id": "t3_2qyrwp", "likes": null, "no_follow": true, "replies": {"kind": "Listing", "data": {"after": null, "whitelist_status": null, "modhash": "", "dist": null, "children": [{"kind": "t1", "data": {"subreddit_id": "t5_2qm0x", "approved_at_utc": null, "ups": 2, "mod_reason_by": null, "banned_by": null, "removal_reason": null, "link_id": "t3_2qyrwp", "likes": null, "no_follow": true, "replies": {"kind": "Listing", "data": {"after": null, "whitelist_status": null, "modhash": "", "dist": null, "children": [{"kind": "t1", "data": {"subreddit_id": "t5_2qm0x", "approved_at_utc": null, "ups": 1, "mod_reason_by": null, "banned_by": null, "removal_reason": null, "link_id": "t3_2qyrwp", "likes": null, "no_follow": true, "replies": "", "user_reports": [], "saved": false, "id": "cnb09dh", "banned_at_utc": null, "mod_reason_title": null, "gilded": 0, "archived": true, "report_reasons": null, "author": "-gogo-", "can_mod_post": false, "send_replies": true, "parent_id": "t1_cnay6iz", "score": 1, "approved_by": null, "downs": 0, "body": "He looks like such a great, handsome guy! I'm so sorry. I wish you peace and blessings from here on out. If you're able, post a picture when you get your new best friend.\n\nHappy New Year!", "edited": false, "author_flair_css_class": null, "collapsed": false, "is_submitter": false, "collapsed_reason": null, "body_html": "&lt;div class=\"md\"&gt;&lt;p&gt;He looks like such a great, handsome guy! I&amp;#39;m so sorry. I wish you peace and blessings from here on out. If you&amp;#39;re able, post a picture when you get your new best friend.&lt;/p&gt;\n\n&lt;p&gt;Happy New Year!&lt;/p&gt;\n&lt;/div&gt;", "subreddit_type": "public", "can_gild": true, "subreddit": "ptsd", "name": "t1_cnb09dh", "score_hidden": false, "permalink": "/r/ptsd/comments/2qyrwp/has_a_therapy_dog_helped_anyone_potential_tw/cnb09dh/", "num_reports": null, "stickied": false, "created": 1420120798.0, "author_flair_text": null, "created_utc": 1420091998.0, "subreddit_name_prefixed": "r/ptsd", "controversiality": 0, "depth": 2, "mod_reports": [], "mod_note": null, "distinguished": null}}, {"kind": "t1", "data": {"subreddit_id": "t5_2qm0x", "approved_at_utc": null, "ups": 3, "mod_reason_by": null, "banned_by": null, "removal_reason": null, "link_id": "t3_2qyrwp", "likes": null, "no_follow": true, "replies": "", "user_reports": [], "saved": false, "id": "cnayn46", "banned_at_utc": null, "mod_reason_title": null, "gilded": 0, "archived": true, "report_reasons": null, "author": "crazy_cat_broad", "can_mod_post": false, "send_replies": true, "parent_id": "t1_cnay6iz", "score": 3, "approved_by": null, "downs": 0, "body": "So sorry for your loss, what a sweetie.", "edited": false, "author_flair_css_class": null, "collapsed": false, "is_submitter": false, "collapsed_reason": null, "body_html": "&lt;div class=\"md\"&gt;&lt;p&gt;So sorry for your loss, what a sweetie.&lt;/p&gt;\n&lt;/div&gt;", "subreddit_type": "public", "can_gild": true, "subreddit": "ptsd", "name": "t1_cnayn46", "score_hidden": false, "permalink": "/r/ptsd/comments/2qyrwp/has_a_therapy_dog_helped_anyone_potential_tw/cnayn46/", "num_reports": null, "stickied": false, "created": 1420115609.0, "author_flair_text": null, "created_utc": 1420086809.0, "subreddit_name_prefixed": "r/ptsd", "controversiality": 0, "depth": 2, "mod_reports": [], "mod_note": null, "distinguished": null}}], "before": null}}, "user_reports": [], "saved": false, "id": "cnay6iz", "banned_at_utc": null, "mod_reason_title": null, "gilded": 0, "archived": true, "report_reasons": null, "author": "jmattick", "can_mod_post": false, "send_replies": true, "parent_id": "t1_cnaw7mv", "score": 2, "approved_by": null, "downs": 0, "body": "That's it, it's hard to post this but this the last picture of[ Murphy before the incident.](http://i.imgur.com/M8A7w4I.jpg)\n\nBig ol bundle of love I got at the shelter for free, neutering and shots included.", "edited": false, "author_flair_css_class": null, "collapsed": false, "is_submitter": true, "collapsed_reason": null, "body_html": "&lt;div class=\"md\"&gt;&lt;p&gt;That&amp;#39;s it, it&amp;#39;s hard to post this but this the last picture of&lt;a href=\"http://i.imgur.com/M8A7w4I.jpg\"&gt; Murphy before the incident.&lt;/a&gt;&lt;/p&gt;\n\n&lt;p&gt;Big ol bundle of love I got at the shelter for free, neutering and shots included.&lt;/p&gt;\n&lt;/div&gt;", "subreddit_type": "public", "can_gild": true, "subreddit": "ptsd", "name": "t1_cnay6iz", "score_hidden": false, "permalink": "/r/ptsd/comments/2qyrwp/has_a_therapy_dog_helped_anyone_potential_tw/cnay6iz/", "num_reports": null, "stickied": false, "created": 1420114279.0, "author_flair_text": null, "created_utc": 1420085479.0, "subreddit_name_prefixed": "r/ptsd", "controversiality": 0, "depth": 1, "mod_reports": [], "mod_note": null, "distinguished": null}}], "before": null}}, "user_reports": [], "saved": false, "id": "cnaw7mv", "banned_at_utc": null, "mod_reason_title": null, "gilded": 0, "archived": true, "report_reasons": null, "author": "-gogo-", "can_mod_post": false, "send_replies": true, "parent_id": "t3_2qyrwp", "score": 7, "approved_by": null, "downs": 0, "body": "Lord have mercy sugar, you go on and get yourself a dog.\n\nA certified pre trained service dog is absolutely wonderful but expensive. If you all can afford it, by all means go get one as soon as you can. If you can't afford one, any dog can be certified. Your therapist should be able to help you with the paperwork. It's not hard and it should not be overwhelming.\n\nI got mine for free from Craigslist. She's the most snuggly, smartest, most sensitive labradoodle there ever was. I also got an orange service dog vest off a website. My therapist signed a paper I printed out to get her registered. Not a big deal at all.\n\nNow if I could just keep her from stealing my socks...", "edited": false, "author_flair_css_class": null, "collapsed": false, "is_submitter": false, "collapsed_reason": null, "body_html": "&lt;div class=\"md\"&gt;&lt;p&gt;Lord have mercy sugar, you go on and get yourself a dog.&lt;/p&gt;\n\n&lt;p&gt;A certified pre trained service dog is absolutely wonderful but expensive. If you all can afford it, by all means go get one as soon as you can. If you can&amp;#39;t afford one, any dog can be certified. Your therapist should be able to help you with the paperwork. It&amp;#39;s not hard and it should not be overwhelming.&lt;/p&gt;\n\n&lt;p&gt;I got mine for free from Craigslist. She&amp;#39;s the most snuggly, smartest, most sensitive labradoodle there ever was. I also got an orange service dog vest off a website. My therapist signed a paper I printed out to get her registered. Not a big deal at all.&lt;/p&gt;\n\n&lt;p&gt;Now if I could just keep her from stealing my socks...&lt;/p&gt;\n&lt;/div&gt;", "subreddit_type": "public", "can_gild": true, "subreddit": "ptsd", "name": "t1_cnaw7mv", "score_hidden": false, "permalink": "/r/ptsd/comments/2qyrwp/has_a_therapy_dog_helped_anyone_potential_tw/cnaw7mv/", "num_reports": null, "stickied": false, "created": 1420108762.0, "author_flair_text": null, "created_utc": 1420079962.0, "subreddit_name_prefixed": "r/ptsd", "controversiality": 0, "depth": 0, "mod_reports": [], "mod_note": null, "distinguished": null}}, {"kind": "t1", "data": {"subreddit_id": "t5_2qm0x", "approved_at_utc": null, "ups": 3, "mod_reason_by": null, "banned_by": null, "removal_reason": null, "link_id": "t3_2qyrwp", "likes": null, "no_follow": true, "replies": {"kind": "Listing", "data": {"after": null, "whitelist_status": null, "modhash": "", "dist": null, "children": [{"kind": "t1", "data": {"subreddit_id": "t5_2qm0x", "approved_at_utc": null, "ups": 3, "mod_reason_by": null, "banned_by": null, "removal_reason": null, "link_id": "t3_2qyrwp", "likes": null, "no_follow": true, "replies": {"kind": "Listing", "data": {"after": null, "whitelist_status": null, "modhash": "", "dist": null, "children": [{"kind": "t1", "data": {"subreddit_id": "t5_2qm0x", "approved_at_utc": null, "ups": 2, "mod_reason_by": null, "banned_by": null, "removal_reason": null, "link_id": "t3_2qyrwp", "likes": null, "no_follow": true, "replies": {"kind": "Listing", "data": {"after": null, "whitelist_status": null, "modhash": "", "dist": null, "children": [{"kind": "t1", "data": {"subreddit_id": "t5_2qm0x", "approved_at_utc": null, "ups": 2, "mod_reason_by": null, "banned_by": null, "removal_reason": null, "link_id": "t3_2qyrwp", "likes": null, "no_follow": true, "replies": {"kind": "Listing", "data": {"after": null, "whitelist_status": null, "modhash": "", "dist": null, "children": [{"kind": "t1", "data": {"subreddit_id": "t5_2qm0x", "approved_at_utc": null, "ups": 1, "mod_reason_by": null, "banned_by": null, "removal_reason": null, "link_id": "t3_2qyrwp", "likes": null, "no_follow": true, "replies": "", "user_reports": [], "saved": false, "id": "cnayhcp", "banned_at_utc": null, "mod_reason_title": null, "gilded": 0, "archived": true, "report_reasons": null, "author": "hulahulagirl", "can_mod_post": false, "send_replies": true, "parent_id": "t1_cnaxr5d", "score": 1, "approved_by": null, "downs": 0, "body": "Wow. Sorry I have no advice to give. Just good luck.", "edited": false, "author_flair_css_class": null, "collapsed": false, "is_submitter": false, "collapsed_reason": null, "body_html": "&lt;div class=\"md\"&gt;&lt;p&gt;Wow. Sorry I have no advice to give. Just good luck.&lt;/p&gt;\n&lt;/div&gt;", "subreddit_type": "public", "can_gild": true, "subreddit": "ptsd", "name": "t1_cnayhcp", "score_hidden": false, "permalink": "/r/ptsd/comments/2qyrwp/has_a_therapy_dog_helped_anyone_potential_tw/cnayhcp/", "num_reports": null, "stickied": false, "created": 1420115143.0, "author_flair_text": null, "created_utc": 1420086343.0, "subreddit_name_prefixed": "r/ptsd", "controversiality": 0, "depth": 4, "mod_reports": [], "mod_note": null, "distinguished": null}}], "before": null}}, "user_reports": [], "saved": false, "id": "cnaxr5d", "banned_at_utc": null, "mod_reason_title": null, "gilded": 0, "archived": true, "report_reasons": null, "author": "jmattick", "can_mod_post": false, "send_replies": true, "parent_id": "t1_cnax4ss", "score": 2, "approved_by": null, "downs": 0, "body": "That's the thing, we aren't on paper anywhere, changed numbers, all mail goes to a PO box, etc. I just happen to know where he lives due to court reporting of probation. You have to report in whenever there is an address change.\n\nCoincidentally enough, after he attempted to commit suicide (this was about a month after he got out of jail... i'd say october), he was taken to a halfway house where my girfriends brother was and they ended up rooming together so I got to know exactly what was going on. I even broke things off with her \"just in case\" it got back to him where I was staying and I moved again.\n\nThe protection order, should he violate it, he's looking at 2 to 5.\n\nBut understand, and this is something my therapist has forced into my skull. We cannot keep running. We MUST stand our ground. He is NOT the victim so he should not be treated as such. We should move on as if he never existed.\n\nWhich is what I'm trying to do.", "edited": false, "author_flair_css_class": null, "collapsed": false, "is_submitter": true, "collapsed_reason": null, "body_html": "&lt;div class=\"md\"&gt;&lt;p&gt;That&amp;#39;s the thing, we aren&amp;#39;t on paper anywhere, changed numbers, all mail goes to a PO box, etc. I just happen to know where he lives due to court reporting of probation. You have to report in whenever there is an address change.&lt;/p&gt;\n\n&lt;p&gt;Coincidentally enough, after he attempted to commit suicide (this was about a month after he got out of jail... i&amp;#39;d say october), he was taken to a halfway house where my girfriends brother was and they ended up rooming together so I got to know exactly what was going on. I even broke things off with her &amp;quot;just in case&amp;quot; it got back to him where I was staying and I moved again.&lt;/p&gt;\n\n&lt;p&gt;The protection order, should he violate it, he&amp;#39;s looking at 2 to 5.&lt;/p&gt;\n\n&lt;p&gt;But understand, and this is something my therapist has forced into my skull. We cannot keep running. We MUST stand our ground. He is NOT the victim so he should not be treated as such. We should move on as if he never existed.&lt;/p&gt;\n\n&lt;p&gt;Which is what I&amp;#39;m trying to do.&lt;/p&gt;\n&lt;/div&gt;", "subreddit_type": "public", "can_gild": true, "subreddit": "ptsd", "name": "t1_cnaxr5d", "score_hidden": false, "permalink": "/r/ptsd/comments/2qyrwp/has_a_therapy_dog_helped_anyone_potential_tw/cnaxr5d/", "num_reports": null, "stickied": false, "created": 1420113039.0, "author_flair_text": null, "created_utc": 1420084239.0, "subreddit_name_prefixed": "r/ptsd", "controversiality": 0, "depth": 3, "mod_reports": [], "mod_note": null, "distinguished": null}}], "before": null}}, "user_reports": [], "saved": false, "id": "cnax4ss", "banned_at_utc": null, "mod_reason_title": null, "gilded": 0, "archived": true, "report_reasons": null, "author": "hulahulagirl", "can_mod_post": false, "send_replies": true, "parent_id": "t1_cnaur7n", "score": 2, "approved_by": null, "downs": 0, "body": "If your physical safety is probably in danger, you may not want to take on a dog for a while. ? That's a crazy situation. Hope you can stay safe.", "edited": false, "author_flair_css_class": null, "collapsed": false, "is_submitter": false, "collapsed_reason": null, "body_html": "&lt;div class=\"md\"&gt;&lt;p&gt;If your physical safety is probably in danger, you may not want to take on a dog for a while. ? That&amp;#39;s a crazy situation. Hope you can stay safe.&lt;/p&gt;\n&lt;/div&gt;", "subreddit_type": "public", "can_gild": true, "subreddit": "ptsd", "name": "t1_cnax4ss", "score_hidden": false, "permalink": "/r/ptsd/comments/2qyrwp/has_a_therapy_dog_helped_anyone_potential_tw/cnax4ss/", "num_reports": null, "stickied": false, "created": 1420111281.0, "author_flair_text": null, "created_utc": 1420082481.0, "subreddit_name_prefixed": "r/ptsd", "controversiality": 0, "depth": 2, "mod_reports": [], "mod_note": null, "distinguished": null}}], "before": null}}, "user_reports": [], "saved": false, "id": "cnaur7n", "banned_at_utc": null, "mod_reason_title": null, "gilded": 0, "archived": true, "report_reasons": null, "author": "jmattick", "can_mod_post": false, "send_replies": true, "parent_id": "t1_cnau9ow", "score": 3, "approved_by": null, "downs": 0, "body": "That's what happened with Murphy. (TW)\n\nWhen my stepfather beat me the last time, Murphy (a shelter dog I had adopted years back broke through my bedroom door and started to try to fend my stepfather off. Murphy weighed about 110lbs (Lab/Dalmation mix) and was biting him similar to the way a police trained german shepherd attacks what it is pointed toward.\n\nOf course, my stepfather weighs 320 and is built and wasn't a match for Murphy or me. \n\nWe got him out of the house and I took Murphy to my grandparents where I was going to stay until I knew he was in jail. Late one night, I hear Murphy barking and I figure he sees the tractors because there is always lights running up and down the field.\n\nI wake up to check on Murphy and he was dead. His neck was snapped, marks that looked like stabbings but couldn't be disregarded as tooth marks and his snout was gone, hanging by a little piece of tissue. Those were the vet findings.\n\nSo you can tell my apprehension about training a dog. I just need someone and my therapist brought it up. My stepfather is out on probation right now and the protective order is still in place until he violates his probation. He has had no contact with us (me and my mom) and we gave up the house and moved where he wouldn't know, but via public record I am able to keep an eye on his addresses and such.\n\nRight now I'm staying in a hotel because my mom is in the hospital and every movement, every door slam, every creak, every knock sends me into anxiety overdrive. I'm currently sleeping against the door on the hardwood to give you an idea.", "edited": false, "author_flair_css_class": null, "collapsed": false, "is_submitter": true, "collapsed_reason": null, "body_html": "&lt;div class=\"md\"&gt;&lt;p&gt;That&amp;#39;s what happened with Murphy. (TW)&lt;/p&gt;\n\n&lt;p&gt;When my stepfather beat me the last time, Murphy (a shelter dog I had adopted years back broke through my bedroom door and started to try to fend my stepfather off. Murphy weighed about 110lbs (Lab/Dalmation mix) and was biting him similar to the way a police trained german shepherd attacks what it is pointed toward.&lt;/p&gt;\n\n&lt;p&gt;Of course, my stepfather weighs 320 and is built and wasn&amp;#39;t a match for Murphy or me. &lt;/p&gt;\n\n&lt;p&gt;We got him out of the house and I took Murphy to my grandparents where I was going to stay until I knew he was in jail. Late one night, I hear Murphy barking and I figure he sees the tractors because there is always lights running up and down the field.&lt;/p&gt;\n\n&lt;p&gt;I wake up to check on Murphy and he was dead. His neck was snapped, marks that looked like stabbings but couldn&amp;#39;t be disregarded as tooth marks and his snout was gone, hanging by a little piece of tissue. Those were the vet findings.&lt;/p&gt;\n\n&lt;p&gt;So you can tell my apprehension about training a dog. I just need someone and my therapist brought it up. My stepfather is out on probation right now and the protective order is still in place until he violates his probation. He has had no contact with us (me and my mom) and we gave up the house and moved where he wouldn&amp;#39;t know, but via public record I am able to keep an eye on his addresses and such.&lt;/p&gt;\n\n&lt;p&gt;Right now I&amp;#39;m staying in a hotel because my mom is in the hospital and every movement, every door slam, every creak, every knock sends me into anxiety overdrive. I&amp;#39;m currently sleeping against the door on the hardwood to give you an idea.&lt;/p&gt;\n&lt;/div&gt;", "subreddit_type": "public", "can_gild": true, "subreddit": "ptsd", "name": "t1_cnaur7n", "score_hidden": false, "permalink": "/r/ptsd/comments/2qyrwp/has_a_therapy_dog_helped_anyone_potential_tw/cnaur7n/", "num_reports": null, "stickied": false, "created": 1420105058.0, "author_flair_text": null, "created_utc": 1420076258.0, "subreddit_name_prefixed": "r/ptsd", "controversiality": 0, "depth": 1, "mod_reports": [], "mod_note": null, "distinguished": null}}], "before": null}}, "user_reports": [], "saved": false, "id": "cnau9ow", "banned_at_utc": null, "mod_reason_title": null, "gilded": 0, "archived": true, "report_reasons": null, "author": "hulahulagirl", "can_mod_post": false, "send_replies": true, "parent_id": "t3_2qyrwp", "score": 3, "approved_by": null, "downs": 0, "body": "I'm sorry that happened to you. It sounds terrifying. I don't have experience with trained therapy dogs, but I know as well as you do that having any kind of dog, trained or not, is comforting and helpful when you feel overwhelmed. Maybe you could get a shelter dog and work on getting him/her certified as a service dog? That would give you a goal to work toward. Good luck.", "edited": false, "author_flair_css_class": null, "collapsed": false, "is_submitter": false, "collapsed_reason": null, "body_html": "&lt;div class=\"md\"&gt;&lt;p&gt;I&amp;#39;m sorry that happened to you. It sounds terrifying. I don&amp;#39;t have experience with trained therapy dogs, but I know as well as you do that having any kind of dog, trained or not, is comforting and helpful when you feel overwhelmed. Maybe you could get a shelter dog and work on getting him/her certified as a service dog? That would give you a goal to work toward. Good luck.&lt;/p&gt;\n&lt;/div&gt;", "subreddit_type": "public", "can_gild": true, "subreddit": "ptsd", "name": "t1_cnau9ow", "score_hidden": false, "permalink": "/r/ptsd/comments/2qyrwp/has_a_therapy_dog_helped_anyone_potential_tw/cnau9ow/", "num_reports": null, "stickied": false, "created": 1420103870.0, "author_flair_text": null, "created_utc": 1420075070.0, "subreddit_name_prefixed": "r/ptsd", "controversiality": 0, "depth": 0, "mod_reports": [], "mod_note": null, "distinguished": null}}], "before": null}}]